LumosWeb/__init__.py
LumosWeb/api.py
LumosWeb/cli.py
LumosWeb/middleware.py
LumosWeb/orm.py
LumosWeb/response.py
LumosWeb-1.2.0.dist-info/METADATA
LumosWeb-1.2.0.dist-info/WHEEL
LumosWeb-1.2.0.dist-info/entry_points.txt
LumosWeb-1.2.0.dist-info/top_level.txt
LumosWeb-1.2.0.dist-info/RECORD
