Metadata-Version: 2.1
Name: LumosWeb
Version: 1.2.0
Summary: LumosWeb is web framework, simple and effective usage
Author: Sddilora
Author-email: sumeyyedilaradogan@gmail.com
License: MIT
Classifier: Programming Language :: Python :: 3.6
Requires-Python: >=3.6.0
Requires-Dist: Jinja2 (==3.1.2)
Requires-Dist: parse (==1.19.0)
Requires-Dist: requests (==2.31.0)
Requires-Dist: requests-wsgi-adapter (==0.4.1)
Requires-Dist: WebOb (==1.8.7)
Requires-Dist: whitenoise (==6.4.0)
Requires-Dist: Markdown (==3.4.3)
Requires-Dist: Pygments (==2.15.1)
